[
  {
    "date": "2026-06-11",
    "sport": "Soccer",
    "question": "Which player won the Golden Ball (best player) at the 2014 FIFA World Cup despite his team finishing as runners-up?",
    "answer": "Lionel Messi"
  },
  {
    "date": "2026-06-12",
    "sport": "Golf",
    "question": "Which golfer won the 2023 PGA Championship at Oak Hill Country Club, claiming his third major title and first since 2019?",
    "answer": "Collin Morikawa"
  },
  {
    "date": "2026-06-13",
    "sport": "NBA",
    "question": "Only two players have won the NBA MVP award while playing for the same franchise in back-to-back seasons since 2000. Name either one of them.",
    "answer": "Stephen Curry (2015, 2016 with Golden State Warriors) or Karl-Anthony Towns (2024, 2025 with Minnesota Timberwolves)"
  },
  {
    "date": "2026-06-14",
    "sport": "Sports",
    "question": "Which NBA player won Most Valuable Player for the 1999-2000 season?",
    "answer": "Shaquille O'Neal"
  },
  {
    "date": "2026-06-15",
    "sport": "Sports",
    "question": "Who is Manchester United's top premier league goal scorer?",
    "answer": "Wayne Rooney"
  },
  {
    "date": "2026-06-16",
    "sport": "Sports",
    "question": "Which of these countries' national teams qualified for the 2018 FIFA World Cup in Russia?",
    "answer": "Tunisia"
  },
  {
    "date": "2026-06-17",
    "sport": "Sports",
    "question": "At which race was the 2018 F1 Drivers Championship won?",
    "answer": "Mexico"
  },
  {
    "date": "2026-06-18",
    "sport": "Sports",
    "question": "How many soccer players should be on the field at the same time?",
    "answer": "22"
  },
  {
    "date": "2026-06-19",
    "sport": "Sports",
    "question": "What was the year of estabilishment of the Bari Italian Football Club?",
    "answer": "1908"
  },
  {
    "date": "2026-06-20",
    "sport": "Sports",
    "question": "Which football manager won more trophies than any other during his tenure at English football club Manchester United?",
    "answer": "Sir Alex Ferguson"
  },
  {
    "date": "2026-06-21",
    "sport": "Sports",
    "question": "Which of the following player scored a hat-trick during their Manchester United debut?",
    "answer": "Wayne Rooney"
  },
  {
    "date": "2026-06-22",
    "sport": "Sports",
    "question": "What is the name of the \"tool\" used to hit the white ball in snooker or billiards?",
    "answer": "Cue"
  },
  {
    "date": "2026-06-23",
    "sport": "Sports",
    "question": "In what year did Steaua București win the European Cup, actual UEFA Champions League, against FC Barcelona?",
    "answer": "1986"
  },
  {
    "date": "2026-06-24",
    "sport": "Sports",
    "question": "What team did England beat in the semi-final stage to win in the 1966 World Cup final?",
    "answer": "Portugal"
  },
  {
    "date": "2026-06-25",
    "sport": "Sports",
    "question": "Who was the British professional wrestler Shirley Crabtree better known as?",
    "answer": "Big Daddy"
  },
  {
    "date": "2026-06-26",
    "sport": "Sports",
    "question": "Which sport is NOT traditionally played during the Mongolian Naadam festival?",
    "answer": "American Football"
  },
  {
    "date": "2026-06-27",
    "sport": "Sports",
    "question": "Who won the 2015 College Football Playoff (CFP) National Championship?",
    "answer": "Ohio State Buckeyes"
  },
  {
    "date": "2026-06-28",
    "sport": "Sports",
    "question": "What tool lends it's name to a last-stone advantage in an end in Curling?",
    "answer": "Hammer"
  },
  {
    "date": "2026-06-29",
    "sport": "Sports",
    "question": "Who won the UEFA Champions League in 2016?",
    "answer": "Real Madrid C.F."
  },
  {
    "date": "2026-06-30",
    "sport": "Sports",
    "question": "Who won the \"Champions League\" in 1999?",
    "answer": "Manchester United"
  }
]
